bigtree/__init__.py
bigtree/_globals.py
bigtree/_plugins.py
bigtree/py.typed
bigtree/binarytree/__init__.py
bigtree/binarytree/binarytree.py
bigtree/binarytree/construct.py
bigtree/dag/__init__.py
bigtree/dag/construct.py
bigtree/dag/dag.py
bigtree/dag/export.py
bigtree/dag/parsing.py
bigtree/node/__init__.py
bigtree/node/basenode.py
bigtree/node/binarynode.py
bigtree/node/dagnode.py
bigtree/node/node.py
bigtree/tree/__init__.py
bigtree/tree/_query.py
bigtree/tree/helper.py
bigtree/tree/modify.py
bigtree/tree/parsing.py
bigtree/tree/query.py
bigtree/tree/search.py
bigtree/tree/tree.py
bigtree/tree/construct/__init__.py
bigtree/tree/construct/dataframes.py
bigtree/tree/construct/dictionaries.py
bigtree/tree/construct/lists.py
bigtree/tree/construct/render.py
bigtree/tree/construct/strings.py
bigtree/tree/export/__init__.py
bigtree/tree/export/_stdout.py
bigtree/tree/export/_yield_tree.py
bigtree/tree/export/dataframes.py
bigtree/tree/export/dictionaries.py
bigtree/tree/export/images.py
bigtree/tree/export/stdout.py
bigtree/tree/export/vis.py
bigtree/utils/__init__.py
bigtree/utils/assertions.py
bigtree/utils/common.py
bigtree/utils/constants.py
bigtree/utils/exceptions.py
bigtree/utils/groot.py
bigtree/utils/iterators.py
bigtree/utils/plot.py
bigtree/workflows/__init__.py
bigtree/workflows/app_calendar.py
bigtree/workflows/app_todo.py
bigtree-1.3.0.dist-info/METADATA
bigtree-1.3.0.dist-info/WHEEL
bigtree-1.3.0.dist-info/licenses/LICENSE
bigtree-1.3.0.dist-info/RECORD
