Metadata-Version: 2.4
Name: bigtree
Version: 1.3.0
Summary: Tree Implementation and Methods for Python, integrated with list, dictionary, pandas and polars DataFrame.
Project-URL: Documentation, https://bigtree.readthedocs.io
Project-URL: Issues, https://github.com/kayjan/bigtree/issues
Project-URL: Discussions, https://github.com/kayjan/bigtree/discussions
Project-URL: Source, https://github.com/kayjan/bigtree
Author-email: Kay Jan <kayjanw@gmail.com>
License: MIT
License-File: LICENSE
Keywords: bigtree,tree
Classifier: Development Status :: 4 - Beta
Classifier: Programming Language :: Python
Classifier: Programming Language :: Python :: 3.10
Classifier: Programming Language :: Python :: 3.11
Classifier: Programming Language :: Python :: 3.12
Classifier: Programming Language :: Python :: 3.13
Classifier: Programming Language :: Python :: Implementation :: CPython
Classifier: Programming Language :: Python :: Implementation :: PyPy
Requires-Python: >=3.10
Provides-Extra: all
Requires-Dist: lark; extra == 'all'
Requires-Dist: matplotlib; extra == 'all'
Requires-Dist: pandas; extra == 'all'
Requires-Dist: pillow; extra == 'all'
Requires-Dist: polars; extra == 'all'
Requires-Dist: pydot; extra == 'all'
Requires-Dist: pyvis; extra == 'all'
Requires-Dist: rich; extra == 'all'
Provides-Extra: image
Requires-Dist: pillow; extra == 'image'
Requires-Dist: pydot; extra == 'image'
Provides-Extra: matplotlib
Requires-Dist: matplotlib; extra == 'matplotlib'
Provides-Extra: pandas
Requires-Dist: pandas; extra == 'pandas'
Provides-Extra: polars
Requires-Dist: polars; extra == 'polars'
Provides-Extra: query
Requires-Dist: lark; extra == 'query'
Provides-Extra: rich
Requires-Dist: rich; extra == 'rich'
Provides-Extra: vis
Requires-Dist: pyvis; extra == 'vis'
